customer/Customer.py
customer/Search.py
customer/Testcustomer.py
customer/Testsearch.py
customer/__init__.py
produce/Testfruit.py
produce/Testinventory.py
produce/__init__.py
produce/fruit.py
produce/inventory.py
fruit_purchase_UX-0.1.dist-info/METADATA
fruit_purchase_UX-0.1.dist-info/WHEEL
fruit_purchase_UX-0.1.dist-info/top_level.txt
fruit_purchase_UX-0.1.dist-info/RECORD
