Metadata-Version: 2.1
Name: fruit-purchase-UX
Version: 0.1
Summary: A test python package for fruit purchase system.
Home-page: https://github.com/ujjwal-upadhyay/DATA533_Project_Group_10_Step3
Author: Ujjwal Upadhyay and Xiaoxiao Fu
Author-email: upadhyay.ujjwal007@gmail.com
License: MIT
Platform: UNKNOWN
